jira_oauth/__init__.py
jira_oauth/console.py
jira_oauth-0.1.12.dist-info/entry_points.txt
jira_oauth-0.1.12.dist-info/LICENSE
jira_oauth-0.1.12.dist-info/WHEEL
jira_oauth-0.1.12.dist-info/METADATA
jira_oauth-0.1.12.dist-info/RECORD
