Metadata-Version: 2.1
Name: jira-oauth
Version: 0.1.12
Summary: Python library for Jira OAuth 
Home-page: https://github.com/rominf/jira-oauth
License: Apache-2.0
Author: Roman Inflianskas
Author-email: infroma@gmail.com
Requires-Python: >=3.6,<4.0
Classifier: License :: OSI Approved :: Apache Software License
Classifier: Programming Language :: Python :: 3
Classifier: Programming Language :: Python :: 3.6
Classifier: Programming Language :: Python :: 3.7
Classifier: Programming Language :: Python :: 3.8
Requires-Dist: PyJWT (>=1.7,<2.0)
Requires-Dist: aioauth2 (>=0.1.0,<0.2.0)
Requires-Dist: aiohttp (>=3.4,<4.0)
Requires-Dist: asn1crypto (>=0.24.0,<0.25.0)
Requires-Dist: certifi (>=2018.11,<2019.0)
Requires-Dist: cffi (>=1.11,<2.0)
Requires-Dist: chardet (>=3.0,<4.0)
Requires-Dist: click (>=7.0,<8.0)
Requires-Dist: cryptography (>=2.4,<3.0)
Requires-Dist: dataclasses (>=0.6.0,<0.7.0)
Requires-Dist: defusedxml (>=0.5.0,<0.6.0)
Requires-Dist: httplib2 (>=0.12.0,<0.13.0)
Requires-Dist: idna (>=2.8,<3.0)
Requires-Dist: oauth2 (>=1.9,<2.0)
Requires-Dist: oauthlib (>=2.1,<3.0)
Requires-Dist: pbr (>=5.1,<6.0)
Requires-Dist: poetry-version (>=0.1.2,<0.2.0)
Requires-Dist: pycparser (>=2.19,<3.0)
Requires-Dist: six (>=1.11,<2.0)
Requires-Dist: tlslite (>=0.4.9,<0.5.0)
Requires-Dist: urllib3 (>=1.24,<2.0)
Requires-Dist: yarl (>=1.3,<2.0)
Project-URL: Repository, https://github.com/rominf/jira-oauth
